indicator/V1DomainFinder.py
indicator/V1EmailFinder.py
indicator/V1IpFinder.py
indicator/functions.py
indicator/hashCalculater.py
indicator/indicator.py
indicator/log.py
indicatorintelligence-1.1.1.dist-info/LICENSE
indicatorintelligence-1.1.1.dist-info/METADATA
indicatorintelligence-1.1.1.dist-info/WHEEL
indicatorintelligence-1.1.1.dist-info/RECORD
