Metadata-Version: 2.1
Name: indicatorintelligence
Version: 1.1.1
Summary: 
Author: Your Name
Author-email: osmankandemir00@gmail.com
Requires-Python: >=3.10,<4.0
Classifier: Programming Language :: Python :: 3
Classifier: Programming Language :: Python :: 3.10
Classifier: Programming Language :: Python :: 3.11
Requires-Dist: aiodns (==3.0.0)
Requires-Dist: beautifulsoup4 (==4.11.2)
Requires-Dist: build (==0.10.0)
Requires-Dist: certifi (==2022.12.7)
Requires-Dist: cffi (==1.15.1)
Requires-Dist: charset-normalizer (==3.0.1)
Requires-Dist: dnspython (==1.15.0)
Requires-Dist: filelock (==3.9.0)
Requires-Dist: idna (==3.4)
Requires-Dist: packaging (==23.0)
Requires-Dist: platformdirs (==3.0.0)
Requires-Dist: pycares (==4.3.0)
Requires-Dist: pycparser (==2.21)
Requires-Dist: pyproject-hooks (==1.0.0)
Requires-Dist: requests (==2.28.2)
Requires-Dist: requests-file (==1.5.1)
Requires-Dist: six (==1.16.0)
Requires-Dist: soupsieve (==2.4)
Requires-Dist: tldextract (==3.4.0)
Requires-Dist: tomli (==2.0.1)
Requires-Dist: uritools (==4.0.1)
Requires-Dist: urlextract (==1.8.0)
Requires-Dist: urllib3 (==1.26.14)
